{
  "Mow The Lawn! [Simulator]": {
    "CCU": 187,
    "Visits": 85348425,
    "Ratio": 96
  },
  "Be a Shark": {
    "CCU": 779,
    "Visits": 64003231,
    "Ratio": 88
  },
  "Be a Spider! Tycoon": {
    "CCU": 192,
    "Visits": 111428569,
    "Ratio": 92
  },
  "Ride a Cart Simulator": {
    "CCU": 584,
    "Visits": 148682436,
    "Ratio": 95
  },
  "Draw Tower Race": {
    "CCU": 3565,
    "Visits": 15918710,
    "Ratio": 85
  },
  "Fire Fighting Simulator": {
    "CCU": 45,
    "Visits": 4754162,
    "Ratio": 88
  },
  "Destroy It! Simulator": {
    "CCU": 59,
    "Visits": 19614851,
    "Ratio": 92
  },
  "Be a Tank": {
    "CCU": 222,
    "Visits": 10792071,
    "Ratio": 86
  },
  "Bear Simulator": {
    "CCU": 74,
    "Visits": 6708826,
    "Ratio": 88
  },
  "Baby City! RP": {
    "CCU": 76,
    "Visits": 94687128,
    "Ratio": 77
  },
  "EAT A FRIEND": {
    "CCU": 17,
    "Visits": 8782537,
    "Ratio": 89
  },
  "Be a Pirate": {
    "CCU": 25,
    "Visits": 1429709,
    "Ratio": 82
  },
  "Be a Snake": {
    "CCU": 1118,
    "Visits": 68047055,
    "Ratio": 88
  },
  "Be a Dragon": {
    "CCU": 130,
    "Visits": 8856576,
    "Ratio": 89
  },
  "Be a Tornado": {
    "CCU": 448,
    "Visits": 45305509,
    "Ratio": 91
  },
  "Drive and Crash Into People": {
    "CCU": 45,
    "Visits": 4321225,
    "Ratio": 81
  }
}