{
  "Be a Tornado": {
    "CCU": 610,
    "Visits": 26038651,
    "Ratio": 91
  },
  "Be a Snake": {
    "CCU": 1162,
    "Visits": 47137654,
    "Ratio": 89
  },
  "Fire Fighting Simulator": {
    "CCU": 66,
    "Visits": 3700146,
    "Ratio": 88
  },
  "Be a Spider! Tycoon": {
    "CCU": 819,
    "Visits": 107565561,
    "Ratio": 92
  },
  "Ride a Cart Simulator": {
    "CCU": 1284,
    "Visits": 139071395,
    "Ratio": 95
  },
  "Be a Shark": {
    "CCU": 1275,
    "Visits": 48679969,
    "Ratio": 88
  },
  "Baby City! RP": {
    "CCU": 287,
    "Visits": 89484823,
    "Ratio": 77
  },
  "Mow The Lawn! [Simulator]": {
    "CCU": 358,
    "Visits": 81319928,
    "Ratio": 96
  },
  "EAT A FRIEND": {
    "CCU": 56,
    "Visits": 7763132,
    "Ratio": 89
  },
  "Bear Simulator": {
    "CCU": 166,
    "Visits": 4413318,
    "Ratio": 89
  },
  "Drive and Crash Into People": {
    "CCU": 67,
    "Visits": 2403729,
    "Ratio": 87
  },
  "Be a Dragon": {
    "CCU": 235,
    "Visits": 4592736,
    "Ratio": 88
  },
  "Be a Tank": {
    "CCU": 302,
    "Visits": 5829761,
    "Ratio": 85
  },
  "Destroy It! Simulator": {
    "CCU": 183,
    "Visits": 18194448,
    "Ratio": 92
  }
}