{
  "Ride a Cart Simulator": {
    "CCU": 2022,
    "Visits": 133136044,
    "Ratio": 95
  },
  "Be a Tornado": {
    "CCU": 1182,
    "Visits": 21836759,
    "Ratio": 91
  },
  "Be a Snake": {
    "CCU": 2453,
    "Visits": 36988455,
    "Ratio": 89
  },
  "Be a Spider! Tycoon": {
    "CCU": 266,
    "Visits": 106421475,
    "Ratio": 92
  },
  "Be a Shark": {
    "CCU": 890,
    "Visits": 42305962,
    "Ratio": 88
  },
  "Fire Fighting Simulator": {
    "CCU": 43,
    "Visits": 3372279,
    "Ratio": 88
  },
  "EAT A FRIEND": {
    "CCU": 109,
    "Visits": 7234838,
    "Ratio": 89
  },
  "Baby City! RP": {
    "CCU": 72,
    "Visits": 86933862,
    "Ratio": 77
  },
  "Bear Simulator": {
    "CCU": 386,
    "Visits": 3002288,
    "Ratio": 88
  },
  "Be a Dragon": {
    "CCU": 798,
    "Visits": 2535187,
    "Ratio": 88
  },
  "Drive and Crash Into People": {
    "CCU": 421,
    "Visits": 1490080,
    "Ratio": 86
  },
  "Mow The Lawn! [Simulator]": {
    "CCU": 352,
    "Visits": 79912823,
    "Ratio": 96
  },
  "Destroy It! Simulator": {
    "CCU": 97,
    "Visits": 17781108,
    "Ratio": 92
  },
  "Be a Tank": {
    "CCU": 609,
    "Visits": 4090896,
    "Ratio": 85
  }
}