{
  "Be a Tornado": {
    "CCU": 355,
    "Visits": 57846172,
    "Ratio": 91
  },
  "Be a Snake": {
    "CCU": 1100,
    "Visits": 94502822,
    "Ratio": 88
  },
  "Fire Fighting Simulator": {
    "CCU": 0,
    "Visits": 5537217,
    "Ratio": 88
  },
  "Ride a Cart Simulator": {
    "CCU": 166,
    "Visits": 155908926,
    "Ratio": 95
  },
  "Be a Spider! Tycoon": {
    "CCU": 92,
    "Visits": 114965648,
    "Ratio": 92
  },
  "Be a Shark": {
    "CCU": 534,
    "Visits": 80710214,
    "Ratio": 88
  },
  "Mow The Lawn! [Simulator]": {
    "CCU": 148,
    "Visits": 90065771,
    "Ratio": 96
  },
  "EAT A FRIEND": {
    "CCU": 6,
    "Visits": 9261092,
    "Ratio": 89
  },
  "Baby City! RP": {
    "CCU": 47,
    "Visits": 96957714,
    "Ratio": 77
  },
  "Destroy It! Simulator": {
    "CCU": 66,
    "Visits": 20695614,
    "Ratio": 92
  },
  "Bear Simulator": {
    "CCU": 28,
    "Visits": 8593579,
    "Ratio": 88
  },
  "Drive and Crash Into People": {
    "CCU": 45,
    "Visits": 5599885,
    "Ratio": 81
  },
  "Be a Dragon": {
    "CCU": 112,
    "Visits": 12668147,
    "Ratio": 89
  },
  "Be a Tank": {
    "CCU": 237,
    "Visits": 18566618,
    "Ratio": 86
  },
  "Be a Pirate": {
    "CCU": 6,
    "Visits": 2026694,
    "Ratio": 81
  },
  "Draw Tower Race": {
    "CCU": 0,
    "Visits": 50788837,
    "Ratio": 87
  },
  "Volleyball Legends": {
    "CCU": 51000,
    "Visits": 862510122,
    "Ratio": 96
  }
}