{
  "Be a Tornado": {
    "CCU": 156,
    "Visits": 60754428,
    "Ratio": 91
  },
  "Be a Snake": {
    "CCU": 691,
    "Visits": 102668945,
    "Ratio": 88
  },
  "Fire Fighting Simulator": {
    "CCU": 2,
    "Visits": 5586200,
    "Ratio": 88
  },
  "Ride a Cart Simulator": {
    "CCU": 160,
    "Visits": 156656092,
    "Ratio": 95
  },
  "Be a Spider! Tycoon": {
    "CCU": 70,
    "Visits": 115699134,
    "Ratio": 92
  },
  "Be a Shark": {
    "CCU": 367,
    "Visits": 85133301,
    "Ratio": 88
  },
  "Mow The Lawn! [Simulator]": {
    "CCU": 104,
    "Visits": 91292877,
    "Ratio": 96
  },
  "EAT A FRIEND": {
    "CCU": 13,
    "Visits": 9351388,
    "Ratio": 89
  },
  "Baby City! RP": {
    "CCU": 19,
    "Visits": 97282389,
    "Ratio": 77
  },
  "Destroy It! Simulator": {
    "CCU": 31,
    "Visits": 20881841,
    "Ratio": 92
  },
  "Bear Simulator": {
    "CCU": 19,
    "Visits": 8865900,
    "Ratio": 88
  },
  "Drive and Crash Into People": {
    "CCU": 11,
    "Visits": 5898182,
    "Ratio": 81
  },
  "Be a Dragon": {
    "CCU": 51,
    "Visits": 13401207,
    "Ratio": 89
  },
  "Be a Tank": {
    "CCU": 134,
    "Visits": 20657304,
    "Ratio": 86
  },
  "Be a Pirate": {
    "CCU": 3,
    "Visits": 2109028,
    "Ratio": 80
  },
  "Draw Tower Race": {
    "CCU": 0,
    "Visits": 50788837,
    "Ratio": 87
  },
  "Volleyball Legends": {
    "CCU": 40928,
    "Visits": 1131618353,
    "Ratio": 96
  }
}