{
  "Be a Tornado": {
    "CCU": 580,
    "Visits": 52134885,
    "Ratio": 91
  },
  "Be a Snake": {
    "CCU": 1508,
    "Visits": 81246647,
    "Ratio": 88
  },
  "Ride a Cart Simulator": {
    "CCU": 559,
    "Visits": 153525546,
    "Ratio": 95
  },
  "Mow The Lawn! [Simulator]": {
    "CCU": 197,
    "Visits": 87899582,
    "Ratio": 96
  },
  "Baby City! RP": {
    "CCU": 161,
    "Visits": 96182947,
    "Ratio": 77
  },
  "Be a Shark": {
    "CCU": 590,
    "Visits": 72762228,
    "Ratio": 88
  },
  "Be a Spider! Tycoon": {
    "CCU": 196,
    "Visits": 113439929,
    "Ratio": 92
  },
  "Bear Simulator": {
    "CCU": 82,
    "Visits": 7913583,
    "Ratio": 88
  },
  "Be a Tank": {
    "CCU": 356,
    "Visits": 14580108,
    "Ratio": 86
  },
  "EAT A FRIEND": {
    "CCU": 16,
    "Visits": 9074432,
    "Ratio": 89
  },
  "Destroy It! Simulator": {
    "CCU": 99,
    "Visits": 20257678,
    "Ratio": 92
  },
  "Drive and Crash Into People": {
    "CCU": 33,
    "Visits": 5098885,
    "Ratio": 81
  },
  "Draw Tower Race": {
    "CCU": 2379,
    "Visits": 32912593,
    "Ratio": 87
  },
  "Be a Dragon": {
    "CCU": 143,
    "Visits": 11032962,
    "Ratio": 89
  },
  "Be a Pirate": {
    "CCU": 12,
    "Visits": 1845577,
    "Ratio": 81
  },
  "Volleyball Legends": {
    "CCU": 45688,
    "Visits": 314131097,
    "Ratio": 97
  },
  "Fire Fighting Simulator": {
    "CCU": 10,
    "Visits": 5406101,
    "Ratio": 88
  }
}