{
  "Be a Tornado": {
    "CCU": 410,
    "Visits": 53773349,
    "Ratio": 91
  },
  "Be a Snake": {
    "CCU": 1127,
    "Visits": 84946487,
    "Ratio": 88
  },
  "Fire Fighting Simulator": {
    "CCU": 6,
    "Visits": 5432711,
    "Ratio": 88
  },
  "Ride a Cart Simulator": {
    "CCU": 408,
    "Visits": 154308815,
    "Ratio": 95
  },
  "Be a Spider! Tycoon": {
    "CCU": 169,
    "Visits": 113777156,
    "Ratio": 92
  },
  "Be a Shark": {
    "CCU": 634,
    "Visits": 74468640,
    "Ratio": 88
  },
  "Mow The Lawn! [Simulator]": {
    "CCU": 234,
    "Visits": 88375406,
    "Ratio": 96
  },
  "EAT A FRIEND": {
    "CCU": 17,
    "Visits": 9132177,
    "Ratio": 89
  },
  "Baby City! RP": {
    "CCU": 106,
    "Visits": 96444852,
    "Ratio": 77
  },
  "Destroy It! Simulator": {
    "CCU": 39,
    "Visits": 20360520,
    "Ratio": 92
  },
  "Bear Simulator": {
    "CCU": 57,
    "Visits": 8117974,
    "Ratio": 88
  },
  "Drive and Crash Into People": {
    "CCU": 27,
    "Visits": 5221154,
    "Ratio": 81
  },
  "Be a Dragon": {
    "CCU": 118,
    "Visits": 11434307,
    "Ratio": 89
  },
  "Be a Tank": {
    "CCU": 144,
    "Visits": 15450405,
    "Ratio": 86
  },
  "Be a Pirate": {
    "CCU": 11,
    "Visits": 1902075,
    "Ratio": 81
  },
  "Draw Tower Race": {
    "CCU": 3028,
    "Visits": 37658229,
    "Ratio": 87
  },
  "Volleyball Legends": {
    "CCU": 70019,
    "Visits": 425018759,
    "Ratio": 97
  }
}