{
  "Be a Tornado": {
    "CCU": 279,
    "Visits": 54169771,
    "Ratio": 91
  },
  "Be a Snake": {
    "CCU": 620,
    "Visits": 85640414,
    "Ratio": 88
  },
  "Fire Fighting Simulator": {
    "CCU": 3,
    "Visits": 5439118,
    "Ratio": 88
  },
  "Ride a Cart Simulator": {
    "CCU": 345,
    "Visits": 154506715,
    "Ratio": 95
  },
  "Be a Spider! Tycoon": {
    "CCU": 109,
    "Visits": 113863799,
    "Ratio": 92
  },
  "Be a Shark": {
    "CCU": 481,
    "Visits": 74904663,
    "Ratio": 88
  },
  "Mow The Lawn! [Simulator]": {
    "CCU": 87,
    "Visits": 88500728,
    "Ratio": 96
  },
  "EAT A FRIEND": {
    "CCU": 10,
    "Visits": 9143725,
    "Ratio": 89
  },
  "Baby City! RP": {
    "CCU": 31,
    "Visits": 96508406,
    "Ratio": 77
  },
  "Destroy It! Simulator": {
    "CCU": 11,
    "Visits": 20383466,
    "Ratio": 92
  },
  "Bear Simulator": {
    "CCU": 51,
    "Visits": 8165040,
    "Ratio": 88
  },
  "Drive and Crash Into People": {
    "CCU": 11,
    "Visits": 5246945,
    "Ratio": 81
  },
  "Be a Dragon": {
    "CCU": 73,
    "Visits": 11535822,
    "Ratio": 89
  },
  "Be a Tank": {
    "CCU": 224,
    "Visits": 15673093,
    "Ratio": 86
  },
  "Be a Pirate": {
    "CCU": 9,
    "Visits": 1918325,
    "Ratio": 81
  },
  "Draw Tower Race": {
    "CCU": 1459,
    "Visits": 39136105,
    "Ratio": 87
  },
  "Volleyball Legends": {
    "CCU": 51587,
    "Visits": 460364081,
    "Ratio": 97
  }
}