{
  "Be a Tornado": {
    "CCU": 393,
    "Visits": 39723418,
    "Ratio": 91
  },
  "Be a Snake": {
    "CCU": 582,
    "Visits": 60276120,
    "Ratio": 88
  },
  "Ride a Cart Simulator": {
    "CCU": 576,
    "Visits": 145173576,
    "Ratio": 95
  },
  "Fire Fighting Simulator": {
    "CCU": 33,
    "Visits": 4323577,
    "Ratio": 88
  },
  "Be a Spider! Tycoon": {
    "CCU": 100,
    "Visits": 110303528,
    "Ratio": 92
  },
  "Be a Shark": {
    "CCU": 449,
    "Visits": 58035476,
    "Ratio": 88
  },
  "Mow The Lawn! [Simulator]": {
    "CCU": 232,
    "Visits": 83976746,
    "Ratio": 96
  },
  "Destroy It! Simulator": {
    "CCU": 86,
    "Visits": 19137628,
    "Ratio": 92
  },
  "Baby City! RP": {
    "CCU": 85,
    "Visits": 93775851,
    "Ratio": 77
  },
  "Drive and Crash Into People": {
    "CCU": 188,
    "Visits": 3476128,
    "Ratio": 84
  },
  "Be a Dragon": {
    "CCU": 90,
    "Visits": 7194481,
    "Ratio": 89
  },
  "Bear Simulator": {
    "CCU": 44,
    "Visits": 5917367,
    "Ratio": 88
  },
  "EAT A FRIEND": {
    "CCU": 22,
    "Visits": 8538176,
    "Ratio": 89
  },
  "Be a Tank": {
    "CCU": 151,
    "Visits": 8763308,
    "Ratio": 86
  },
  "Draw Tower Race": {
    "CCU": 34,
    "Visits": 148880,
    "Ratio": 80
  },
  "Be a Pirate": {
    "CCU": 36,
    "Visits": 1053528,
    "Ratio": 83
  }
}