{
  "Be a Tornado": {
    "CCU": 643,
    "Visits": 39846952,
    "Ratio": 91
  },
  "Be a Snake": {
    "CCU": 834,
    "Visits": 60494283,
    "Ratio": 88
  },
  "Be a Spider! Tycoon": {
    "CCU": 154,
    "Visits": 110329967,
    "Ratio": 92
  },
  "Fire Fighting Simulator": {
    "CCU": 62,
    "Visits": 4337183,
    "Ratio": 88
  },
  "Be a Shark": {
    "CCU": 600,
    "Visits": 58177051,
    "Ratio": 88
  },
  "Ride a Cart Simulator": {
    "CCU": 648,
    "Visits": 145270290,
    "Ratio": 95
  },
  "Mow The Lawn! [Simulator]": {
    "CCU": 156,
    "Visits": 84017456,
    "Ratio": 96
  },
  "Baby City! RP": {
    "CCU": 172,
    "Visits": 93809487,
    "Ratio": 77
  },
  "EAT A FRIEND": {
    "CCU": 44,
    "Visits": 8546088,
    "Ratio": 89
  },
  "Bear Simulator": {
    "CCU": 78,
    "Visits": 5936109,
    "Ratio": 88
  },
  "Drive and Crash Into People": {
    "CCU": 138,
    "Visits": 3552451,
    "Ratio": 83
  },
  "Destroy It! Simulator": {
    "CCU": 117,
    "Visits": 19152027,
    "Ratio": 92
  },
  "Be a Tank": {
    "CCU": 209,
    "Visits": 8810064,
    "Ratio": 86
  },
  "Be a Pirate": {
    "CCU": 55,
    "Visits": 1067585,
    "Ratio": 83
  },
  "Draw Tower Race": {
    "CCU": 37,
    "Visits": 163400,
    "Ratio": 79
  },
  "Be a Dragon": {
    "CCU": 168,
    "Visits": 7229270,
    "Ratio": 89
  }
}