{
  "Be a Tornado": {
    "CCU": 757,
    "Visits": 27634354,
    "Ratio": 91
  },
  "Be a Snake": {
    "CCU": 710,
    "Visits": 49569180,
    "Ratio": 89
  },
  "Ride a Cart Simulator": {
    "CCU": 781,
    "Visits": 140624678,
    "Ratio": 95
  },
  "Fire Fighting Simulator": {
    "CCU": 35,
    "Visits": 3842627,
    "Ratio": 88
  },
  "Be a Shark": {
    "CCU": 597,
    "Visits": 51148632,
    "Ratio": 88
  },
  "Mow The Lawn! [Simulator]": {
    "CCU": 231,
    "Visits": 81940781,
    "Ratio": 96
  },
  "Baby City! RP": {
    "CCU": 509,
    "Visits": 91829331,
    "Ratio": 77
  },
  "EAT A FRIEND": {
    "CCU": 53,
    "Visits": 7948030,
    "Ratio": 89
  },
  "Destroy It! Simulator": {
    "CCU": 135,
    "Visits": 18437835,
    "Ratio": 92
  },
  "Bear Simulator": {
    "CCU": 96,
    "Visits": 4804623,
    "Ratio": 89
  },
  "Be a Tank": {
    "CCU": 185,
    "Visits": 6511560,
    "Ratio": 86
  },
  "Drive and Crash Into People": {
    "CCU": 42,
    "Visits": 2618086,
    "Ratio": 87
  },
  "Be a Dragon": {
    "CCU": 166,
    "Visits": 5199239,
    "Ratio": 89
  },
  "Be a Spider! Tycoon": {
    "CCU": 308,
    "Visits": 108744914,
    "Ratio": 92
  }
}