{
  "Be a Tornado": {
    "CCU": 509,
    "Visits": 45363371,
    "Ratio": 91
  },
  "Be a Shark": {
    "CCU": 947,
    "Visits": 64087905,
    "Ratio": 88
  },
  "Be a Spider! Tycoon": {
    "CCU": 310,
    "Visits": 111446186,
    "Ratio": 92
  },
  "Ride a Cart Simulator": {
    "CCU": 728,
    "Visits": 148726149,
    "Ratio": 95
  },
  "Mow The Lawn! [Simulator]": {
    "CCU": 231,
    "Visits": 85364072,
    "Ratio": 96
  },
  "Bear Simulator": {
    "CCU": 113,
    "Visits": 6719492,
    "Ratio": 88
  },
  "Be a Pirate": {
    "CCU": 22,
    "Visits": 1433108,
    "Ratio": 82
  },
  "Draw Tower Race": {
    "CCU": 4587,
    "Visits": 16188469,
    "Ratio": 85
  },
  "Drive and Crash Into People": {
    "CCU": 38,
    "Visits": 4327977,
    "Ratio": 81
  },
  "Be a Tank": {
    "CCU": 333,
    "Visits": 10822445,
    "Ratio": 86
  },
  "Destroy It! Simulator": {
    "CCU": 86,
    "Visits": 19621276,
    "Ratio": 92
  },
  "Be a Dragon": {
    "CCU": 210,
    "Visits": 8877851,
    "Ratio": 89
  },
  "EAT A FRIEND": {
    "CCU": 26,
    "Visits": 8785875,
    "Ratio": 89
  },
  "Be a Snake": {
    "CCU": 1219,
    "Visits": 68143714,
    "Ratio": 88
  },
  "Fire Fighting Simulator": {
    "CCU": 55,
    "Visits": 4763260,
    "Ratio": 88
  },
  "Baby City! RP": {
    "CCU": 153,
    "Visits": 94697608,
    "Ratio": 77
  }
}