{
  "Be a Tornado": {
    "CCU": 351,
    "Visits": 61464660,
    "Ratio": 91
  },
  "Be a Snake": {
    "CCU": 1236,
    "Visits": 104751655,
    "Ratio": 88
  },
  "Fire Fighting Simulator": {
    "CCU": 2,
    "Visits": 5593911,
    "Ratio": 88
  },
  "Ride a Cart Simulator": {
    "CCU": 143,
    "Visits": 156822344,
    "Ratio": 95
  },
  "Be a Spider! Tycoon": {
    "CCU": 88,
    "Visits": 115820347,
    "Ratio": 92
  },
  "Be a Shark": {
    "CCU": 479,
    "Visits": 86390148,
    "Ratio": 88
  },
  "Mow The Lawn! [Simulator]": {
    "CCU": 180,
    "Visits": 91593326,
    "Ratio": 96
  },
  "EAT A FRIEND": {
    "CCU": 8,
    "Visits": 9372816,
    "Ratio": 89
  },
  "Baby City! RP": {
    "CCU": 65,
    "Visits": 97397449,
    "Ratio": 77
  },
  "Destroy It! Simulator": {
    "CCU": 29,
    "Visits": 20917804,
    "Ratio": 92
  },
  "Bear Simulator": {
    "CCU": 32,
    "Visits": 8956117,
    "Ratio": 88
  },
  "Drive and Crash Into People": {
    "CCU": 26,
    "Visits": 5958395,
    "Ratio": 81
  },
  "Be a Dragon": {
    "CCU": 113,
    "Visits": 13606494,
    "Ratio": 89
  },
  "Be a Tank": {
    "CCU": 143,
    "Visits": 21102242,
    "Ratio": 86
  },
  "Be a Pirate": {
    "CCU": 2,
    "Visits": 2125849,
    "Ratio": 80
  },
  "Draw Tower Race": {
    "CCU": 0,
    "Visits": 50788837,
    "Ratio": 87
  },
  "Volleyball Legends": {
    "CCU": 69553,
    "Visits": 1199541554,
    "Ratio": 96
  }
}