{
  "Be a Snake": {
    "CCU": 807,
    "Visits": 76731181,
    "Ratio": 88
  },
  "Ride a Cart Simulator": {
    "CCU": 539,
    "Visits": 152285508,
    "Ratio": 95
  },
  "Fire Fighting Simulator": {
    "CCU": 12,
    "Visits": 5359946,
    "Ratio": 88
  },
  "Be a Spider! Tycoon": {
    "CCU": 157,
    "Visits": 112789033,
    "Ratio": 92
  },
  "Be a Shark": {
    "CCU": 504,
    "Visits": 70236317,
    "Ratio": 88
  },
  "Destroy It! Simulator": {
    "CCU": 64,
    "Visits": 20069469,
    "Ratio": 92
  },
  "Mow The Lawn! [Simulator]": {
    "CCU": 211,
    "Visits": 87057642,
    "Ratio": 96
  },
  "Baby City! RP": {
    "CCU": 115,
    "Visits": 95753379,
    "Ratio": 77
  },
  "EAT A FRIEND": {
    "CCU": 9,
    "Visits": 8977017,
    "Ratio": 89
  },
  "Be a Dragon": {
    "CCU": 148,
    "Visits": 10433564,
    "Ratio": 89
  },
  "Draw Tower Race": {
    "CCU": 1696,
    "Visits": 27250805,
    "Ratio": 86
  },
  "Be a Pirate": {
    "CCU": 11,
    "Visits": 1736360,
    "Ratio": 81
  },
  "Drive and Crash Into People": {
    "CCU": 41,
    "Visits": 4853524,
    "Ratio": 81
  },
  "Be a Tornado": {
    "CCU": 589,
    "Visits": 49872354,
    "Ratio": 91
  },
  "Volleyball Legends": {
    "CCU": 54646,
    "Visits": 181947555,
    "Ratio": 97
  },
  "Bear Simulator": {
    "CCU": 56,
    "Visits": 7551817,
    "Ratio": 88
  },
  "Be a Tank": {
    "CCU": 239,
    "Visits": 13399471,
    "Ratio": 86
  }
}