{
  "Fire Fighting Simulator": {
    "CCU": 106,
    "Visits": 2947453,
    "Ratio": 88
  },
  "Be a Tornado": {
    "CCU": 1000,
    "Visits": 16725322,
    "Ratio": 91
  },
  "Ride a Cart Simulator": {
    "CCU": 2486,
    "Visits": 126523632,
    "Ratio": 95
  },
  "Be a Snake": {
    "CCU": 2513,
    "Visits": 27753976,
    "Ratio": 89
  },
  "Be a Shark": {
    "CCU": 1096,
    "Visits": 37517321,
    "Ratio": 88
  },
  "Mow The Lawn! [Simulator]": {
    "CCU": 460,
    "Visits": 78337837,
    "Ratio": 96
  },
  "EAT A FRIEND": {
    "CCU": 163,
    "Visits": 6549598,
    "Ratio": 89
  },
  "Be a Spider! Tycoon": {
    "CCU": 322,
    "Visits": 105354956,
    "Ratio": 92
  },
  "Baby City! RP": {
    "CCU": 178,
    "Visits": 86468137,
    "Ratio": 77
  },
  "Destroy It! Simulator": {
    "CCU": 206,
    "Visits": 17293000,
    "Ratio": 92
  }
}