{
  "Be a Tornado": {
    "CCU": 57,
    "Visits": 69492369,
    "Ratio": 91
  },
  "Be a Snake": {
    "CCU": 574,
    "Visits": 137774666,
    "Ratio": 88
  },
  "Fire Fighting Simulator": {
    "CCU": 1,
    "Visits": 5705711,
    "Ratio": 88
  },
  "Ride a Cart Simulator": {
    "CCU": 20,
    "Visits": 158026788,
    "Ratio": 95
  },
  "Be a Spider! Tycoon": {
    "CCU": 49,
    "Visits": 117315584,
    "Ratio": 92
  },
  "Be a Shark": {
    "CCU": 335,
    "Visits": 102350865,
    "Ratio": 88
  },
  "Mow The Lawn! [Simulator]": {
    "CCU": 32,
    "Visits": 93849295,
    "Ratio": 96
  },
  "EAT A FRIEND": {
    "CCU": 1,
    "Visits": 9562776,
    "Ratio": 89
  },
  "Baby City! RP": {
    "CCU": 16,
    "Visits": 98168188,
    "Ratio": 76
  },
  "Destroy It! Simulator": {
    "CCU": 4,
    "Visits": 21386756,
    "Ratio": 92
  },
  "Bear Simulator": {
    "CCU": 21,
    "Visits": 10452803,
    "Ratio": 88
  },
  "Drive and Crash Into People": {
    "CCU": 15,
    "Visits": 6859323,
    "Ratio": 81
  },
  "Be a Dragon": {
    "CCU": 31,
    "Visits": 16772872,
    "Ratio": 89
  },
  "Be a Tank": {
    "CCU": 114,
    "Visits": 28479275,
    "Ratio": 87
  },
  "Be a Pirate": {
    "CCU": 0,
    "Visits": 2333184,
    "Ratio": 81
  },
  "Volleyball Legends": {
    "CCU": 53802,
    "Visits": 2939885372,
    "Ratio": 96
  }
}