{
  "Be a Tornado": {
    "CCU": 81,
    "Visits": 69990843,
    "Ratio": 91
  },
  "Be a Snake": {
    "CCU": 600,
    "Visits": 141242919,
    "Ratio": 87
  },
  "Fire Fighting Simulator": {
    "CCU": 0,
    "Visits": 5713492,
    "Ratio": 88
  },
  "Ride a Cart Simulator": {
    "CCU": 21,
    "Visits": 158106529,
    "Ratio": 95
  },
  "Be a Spider! Tycoon": {
    "CCU": 35,
    "Visits": 117518796,
    "Ratio": 92
  },
  "Be a Shark": {
    "CCU": 298,
    "Visits": 104421156,
    "Ratio": 88
  },
  "Mow The Lawn! [Simulator]": {
    "CCU": 26,
    "Visits": 94039443,
    "Ratio": 96
  },
  "EAT A FRIEND": {
    "CCU": 0,
    "Visits": 9579916,
    "Ratio": 89
  },
  "Baby City! RP": {
    "CCU": 25,
    "Visits": 98321622,
    "Ratio": 76
  },
  "Destroy It! Simulator": {
    "CCU": 1,
    "Visits": 21398962,
    "Ratio": 92
  },
  "Bear Simulator": {
    "CCU": 16,
    "Visits": 10613350,
    "Ratio": 88
  },
  "Drive and Crash Into People": {
    "CCU": 16,
    "Visits": 6953872,
    "Ratio": 81
  },
  "Be a Dragon": {
    "CCU": 62,
    "Visits": 17133111,
    "Ratio": 89
  },
  "Be a Tank": {
    "CCU": 171,
    "Visits": 29482157,
    "Ratio": 87
  },
  "Be a Pirate": {
    "CCU": 0,
    "Visits": 2354500,
    "Ratio": 81
  },
  "Volleyball Legends": {
    "CCU": 32827,
    "Visits": 3142442519,
    "Ratio": 96
  }
}