{
  "Be a Tornado": {
    "CCU": 406,
    "Visits": 56106310,
    "Ratio": 91
  },
  "Be a Snake": {
    "CCU": 962,
    "Visits": 89738056,
    "Ratio": 88
  },
  "Fire Fighting Simulator": {
    "CCU": 18,
    "Visits": 5498596,
    "Ratio": 88
  },
  "Ride a Cart Simulator": {
    "CCU": 264,
    "Visits": 155360534,
    "Ratio": 95
  },
  "Be a Spider! Tycoon": {
    "CCU": 86,
    "Visits": 114436320,
    "Ratio": 92
  },
  "Be a Shark": {
    "CCU": 552,
    "Visits": 77888815,
    "Ratio": 88
  },
  "Mow The Lawn! [Simulator]": {
    "CCU": 211,
    "Visits": 89301845,
    "Ratio": 96
  },
  "EAT A FRIEND": {
    "CCU": 6,
    "Visits": 9211464,
    "Ratio": 89
  },
  "Baby City! RP": {
    "CCU": 62,
    "Visits": 96772613,
    "Ratio": 77
  },
  "Destroy It! Simulator": {
    "CCU": 59,
    "Visits": 20550450,
    "Ratio": 92
  },
  "Bear Simulator": {
    "CCU": 35,
    "Visits": 8418314,
    "Ratio": 88
  },
  "Drive and Crash Into People": {
    "CCU": 33,
    "Visits": 5416598,
    "Ratio": 81
  },
  "Be a Dragon": {
    "CCU": 66,
    "Visits": 12158143,
    "Ratio": 89
  },
  "Be a Tank": {
    "CCU": 309,
    "Visits": 17127471,
    "Ratio": 86
  },
  "Be a Pirate": {
    "CCU": 12,
    "Visits": 1978681,
    "Ratio": 81
  },
  "Draw Tower Race": {
    "CCU": 1554,
    "Visits": 46584358,
    "Ratio": 87
  },
  "Volleyball Legends": {
    "CCU": 54331,
    "Visits": 659677873,
    "Ratio": 96
  }
}