{
  "Be a Tornado": {
    "CCU": 240,
    "Visits": 61703696,
    "Ratio": 91
  },
  "Be a Snake": {
    "CCU": 687,
    "Visits": 105585975,
    "Ratio": 88
  },
  "Fire Fighting Simulator": {
    "CCU": 0,
    "Visits": 5597296,
    "Ratio": 88
  },
  "Ride a Cart Simulator": {
    "CCU": 123,
    "Visits": 156878393,
    "Ratio": 95
  },
  "Be a Spider! Tycoon": {
    "CCU": 69,
    "Visits": 115878592,
    "Ratio": 92
  },
  "Be a Shark": {
    "CCU": 379,
    "Visits": 86852369,
    "Ratio": 88
  },
  "Mow The Lawn! [Simulator]": {
    "CCU": 140,
    "Visits": 91709776,
    "Ratio": 96
  },
  "EAT A FRIEND": {
    "CCU": 8,
    "Visits": 9380078,
    "Ratio": 89
  },
  "Baby City! RP": {
    "CCU": 35,
    "Visits": 97442849,
    "Ratio": 77
  },
  "Destroy It! Simulator": {
    "CCU": 29,
    "Visits": 20929766,
    "Ratio": 92
  },
  "Bear Simulator": {
    "CCU": 15,
    "Visits": 8990107,
    "Ratio": 88
  },
  "Drive and Crash Into People": {
    "CCU": 10,
    "Visits": 5980744,
    "Ratio": 81
  },
  "Be a Dragon": {
    "CCU": 51,
    "Visits": 13690017,
    "Ratio": 89
  },
  "Be a Tank": {
    "CCU": 95,
    "Visits": 21227829,
    "Ratio": 86
  },
  "Be a Pirate": {
    "CCU": 0,
    "Visits": 2131033,
    "Ratio": 80
  },
  "Draw Tower Race": {
    "CCU": 0,
    "Visits": 50788837,
    "Ratio": 87
  },
  "Volleyball Legends": {
    "CCU": 36384,
    "Visits": 1224639984,
    "Ratio": 96
  }
}