{
  "Be a Tornado": {
    "CCU": 311,
    "Visits": 71607145,
    "Ratio": 91
  },
  "Be a Snake": {
    "CCU": 637,
    "Visits": 147403628,
    "Ratio": 87
  },
  "Fire Fighting Simulator": {
    "CCU": 0,
    "Visits": 5715079,
    "Ratio": 88
  },
  "Ride a Cart Simulator": {
    "CCU": 35,
    "Visits": 158244644,
    "Ratio": 95
  },
  "Be a Spider! Tycoon": {
    "CCU": 23,
    "Visits": 117719875,
    "Ratio": 92
  },
  "Be a Shark": {
    "CCU": 357,
    "Visits": 107958133,
    "Ratio": 88
  },
  "Mow The Lawn! [Simulator]": {
    "CCU": 34,
    "Visits": 94377168,
    "Ratio": 96
  },
  "EAT A FRIEND": {
    "CCU": 2,
    "Visits": 9601778,
    "Ratio": 89
  },
  "Baby City! RP": {
    "CCU": 14,
    "Visits": 98670652,
    "Ratio": 76
  },
  "Destroy It! Simulator": {
    "CCU": 2,
    "Visits": 21410113,
    "Ratio": 92
  },
  "Bear Simulator": {
    "CCU": 23,
    "Visits": 10838478,
    "Ratio": 88
  },
  "Drive and Crash Into People": {
    "CCU": 3,
    "Visits": 7072463,
    "Ratio": 81
  },
  "Be a Dragon": {
    "CCU": 59,
    "Visits": 17677169,
    "Ratio": 89
  },
  "Be a Tank": {
    "CCU": 30,
    "Visits": 30450826,
    "Ratio": 87
  },
  "Be a Pirate": {
    "CCU": 0,
    "Visits": 2367207,
    "Ratio": 81
  },
  "Volleyball Legends": {
    "CCU": 46305,
    "Visits": 3409768762,
    "Ratio": 95
  }
}