{
  "Be a Tornado": {
    "CCU": 350,
    "Visits": 58523085,
    "Ratio": 91
  },
  "Be a Snake": {
    "CCU": 1113,
    "Visits": 96161337,
    "Ratio": 88
  },
  "Fire Fighting Simulator": {
    "CCU": 4,
    "Visits": 5545280,
    "Ratio": 88
  },
  "Ride a Cart Simulator": {
    "CCU": 146,
    "Visits": 156067047,
    "Ratio": 95
  },
  "Be a Spider! Tycoon": {
    "CCU": 99,
    "Visits": 115092129,
    "Ratio": 92
  },
  "Be a Shark": {
    "CCU": 496,
    "Visits": 81571147,
    "Ratio": 88
  },
  "Mow The Lawn! [Simulator]": {
    "CCU": 188,
    "Visits": 90321115,
    "Ratio": 96
  },
  "EAT A FRIEND": {
    "CCU": 7,
    "Visits": 9281661,
    "Ratio": 89
  },
  "Baby City! RP": {
    "CCU": 35,
    "Visits": 97027554,
    "Ratio": 77
  },
  "Destroy It! Simulator": {
    "CCU": 33,
    "Visits": 20740803,
    "Ratio": 92
  },
  "Bear Simulator": {
    "CCU": 32,
    "Visits": 8650439,
    "Ratio": 88
  },
  "Drive and Crash Into People": {
    "CCU": 34,
    "Visits": 5704737,
    "Ratio": 81
  },
  "Be a Dragon": {
    "CCU": 85,
    "Visits": 12834442,
    "Ratio": 89
  },
  "Be a Tank": {
    "CCU": 244,
    "Visits": 18962969,
    "Ratio": 86
  },
  "Be a Pirate": {
    "CCU": 5,
    "Visits": 2043783,
    "Ratio": 80
  },
  "Draw Tower Race": {
    "CCU": 0,
    "Visits": 50788837,
    "Ratio": 87
  },
  "Volleyball Legends": {
    "CCU": 62578,
    "Visits": 920517381,
    "Ratio": 96
  }
}