{
  "Be a Tornado": {
    "CCU": 129,
    "Visits": 68079680,
    "Ratio": 91
  },
  "Be a Snake": {
    "CCU": 802,
    "Visits": 128991495,
    "Ratio": 88
  },
  "Fire Fighting Simulator": {
    "CCU": 0,
    "Visits": 5674642,
    "Ratio": 88
  },
  "Ride a Cart Simulator": {
    "CCU": 48,
    "Visits": 157869478,
    "Ratio": 95
  },
  "Be a Spider! Tycoon": {
    "CCU": 33,
    "Visits": 116951514,
    "Ratio": 92
  },
  "Be a Shark": {
    "CCU": 425,
    "Visits": 97700011,
    "Ratio": 88
  },
  "Mow The Lawn! [Simulator]": {
    "CCU": 80,
    "Visits": 93418792,
    "Ratio": 96
  },
  "EAT A FRIEND": {
    "CCU": 2,
    "Visits": 9527937,
    "Ratio": 89
  },
  "Baby City! RP": {
    "CCU": 13,
    "Visits": 97922310,
    "Ratio": 76
  },
  "Destroy It! Simulator": {
    "CCU": 20,
    "Visits": 21295930,
    "Ratio": 92
  },
  "Bear Simulator": {
    "CCU": 28,
    "Visits": 9983386,
    "Ratio": 88
  },
  "Drive and Crash Into People": {
    "CCU": 14,
    "Visits": 6627844,
    "Ratio": 81
  },
  "Be a Dragon": {
    "CCU": 75,
    "Visits": 15944817,
    "Ratio": 89
  },
  "Be a Tank": {
    "CCU": 111,
    "Visits": 26504196,
    "Ratio": 87
  },
  "Be a Pirate": {
    "CCU": 0,
    "Visits": 2292285,
    "Ratio": 80
  },
  "Volleyball Legends": {
    "CCU": 76040,
    "Visits": 2478443548,
    "Ratio": 96
  }
}