{
  "Be a Tornado": {
    "CCU": 1373,
    "Visits": 13575063,
    "Ratio": 91
  },
  "Be a Snake": {
    "CCU": 2636,
    "Visits": 21939368,
    "Ratio": 89
  },
  "Fire Fighting Simulator": {
    "CCU": 54,
    "Visits": 2652847,
    "Ratio": 88
  },
  "Ride a Cart Simulator": {
    "CCU": 2622,
    "Visits": 121933005,
    "Ratio": 95
  },
  "Be a Spider! Tycoon": {
    "CCU": 249,
    "Visits": 104744662,
    "Ratio": 92
  },
  "Be a Shark": {
    "CCU": 887,
    "Visits": 34659246,
    "Ratio": 88
  },
  "EAT A FRIEND": {
    "CCU": 159,
    "Visits": 6065160,
    "Ratio": 89
  },
  "Mow The Lawn! [Simulator]": {
    "CCU": 527,
    "Visits": 77341299,
    "Ratio": 96
  },
  "Baby City! RP": {
    "CCU": 67,
    "Visits": 86196399,
    "Ratio": 77
  },
  "Destroy It! Simulator": {
    "CCU": 73,
    "Visits": 17064634,
    "Ratio": 92
  }
}