{
  "Be a Tornado": {
    "CCU": 183,
    "Visits": 57056269,
    "Ratio": 91
  },
  "Be a Snake": {
    "CCU": 497,
    "Visits": 92130046,
    "Ratio": 88
  },
  "Fire Fighting Simulator": {
    "CCU": 3,
    "Visits": 5520759,
    "Ratio": 88
  },
  "Ride a Cart Simulator": {
    "CCU": 178,
    "Visits": 155636873,
    "Ratio": 95
  },
  "Be a Spider! Tycoon": {
    "CCU": 103,
    "Visits": 114704190,
    "Ratio": 92
  },
  "Be a Shark": {
    "CCU": 334,
    "Visits": 79299828,
    "Ratio": 88
  },
  "Mow The Lawn! [Simulator]": {
    "CCU": 119,
    "Visits": 89626404,
    "Ratio": 96
  },
  "EAT A FRIEND": {
    "CCU": 2,
    "Visits": 9233326,
    "Ratio": 89
  },
  "Baby City! RP": {
    "CCU": 37,
    "Visits": 96859362,
    "Ratio": 77
  },
  "Destroy It! Simulator": {
    "CCU": 38,
    "Visits": 20615965,
    "Ratio": 92
  },
  "Bear Simulator": {
    "CCU": 21,
    "Visits": 8506979,
    "Ratio": 88
  },
  "Drive and Crash Into People": {
    "CCU": 19,
    "Visits": 5500456,
    "Ratio": 81
  },
  "Be a Dragon": {
    "CCU": 53,
    "Visits": 12399573,
    "Ratio": 89
  },
  "Be a Tank": {
    "CCU": 168,
    "Visits": 17838944,
    "Ratio": 86
  },
  "Be a Pirate": {
    "CCU": 6,
    "Visits": 2004261,
    "Ratio": 81
  },
  "Draw Tower Race": {
    "CCU": 934,
    "Visits": 49455054,
    "Ratio": 87
  },
  "Volleyball Legends": {
    "CCU": 44734,
    "Visits": 752941515,
    "Ratio": 96
  }
}