{
  "Be a Tornado": {
    "CCU": 304,
    "Visits": 52854253,
    "Ratio": 91
  },
  "Be a Snake": {
    "CCU": 691,
    "Visits": 83161134,
    "Ratio": 88
  },
  "Be a Spider! Tycoon": {
    "CCU": 65,
    "Visits": 113593579,
    "Ratio": 92
  },
  "Be a Shark": {
    "CCU": 259,
    "Visits": 73557790,
    "Ratio": 88
  },
  "EAT A FRIEND": {
    "CCU": 10,
    "Visits": 9104317,
    "Ratio": 89
  },
  "Drive and Crash Into People": {
    "CCU": 19,
    "Visits": 5161190,
    "Ratio": 81
  },
  "Destroy It! Simulator": {
    "CCU": 40,
    "Visits": 20308024,
    "Ratio": 92
  },
  "Fire Fighting Simulator": {
    "CCU": 2,
    "Visits": 5418466,
    "Ratio": 88
  },
  "Ride a Cart Simulator": {
    "CCU": 300,
    "Visits": 153896123,
    "Ratio": 95
  },
  "Bear Simulator": {
    "CCU": 44,
    "Visits": 8008271,
    "Ratio": 88
  },
  "Draw Tower Race": {
    "CCU": 1276,
    "Visits": 35194704,
    "Ratio": 87
  },
  "Mow The Lawn! [Simulator]": {
    "CCU": 81,
    "Visits": 88102496,
    "Ratio": 96
  },
  "Be a Pirate": {
    "CCU": 6,
    "Visits": 1869946,
    "Ratio": 81
  },
  "Be a Dragon": {
    "CCU": 69,
    "Visits": 11225799,
    "Ratio": 89
  },
  "Volleyball Legends": {
    "CCU": 45031,
    "Visits": 362396071,
    "Ratio": 97
  },
  "Be a Tank": {
    "CCU": 125,
    "Visits": 14983678,
    "Ratio": 86
  },
  "Baby City! RP": {
    "CCU": 37,
    "Visits": 96299944,
    "Ratio": 77
  }
}