{
  "Ride a Cart Simulator": {
    "CCU": 1050,
    "Visits": 150612440,
    "Ratio": 95
  },
  "Be a Spider! Tycoon": {
    "CCU": 159,
    "Visits": 112173477,
    "Ratio": 92
  },
  "Be a Tornado": {
    "CCU": 354,
    "Visits": 47742362,
    "Ratio": 91
  },
  "EAT A FRIEND": {
    "CCU": 9,
    "Visits": 8886253,
    "Ratio": 89
  },
  "Be a Shark": {
    "CCU": 876,
    "Visits": 67457846,
    "Ratio": 88
  },
  "Be a Tank": {
    "CCU": 298,
    "Visits": 12120312,
    "Ratio": 86
  },
  "Fire Fighting Simulator": {
    "CCU": 13,
    "Visits": 5087467,
    "Ratio": 88
  },
  "Baby City! RP": {
    "CCU": 69,
    "Visits": 95243050,
    "Ratio": 77
  },
  "Be a Dragon": {
    "CCU": 155,
    "Visits": 9714971,
    "Ratio": 89
  },
  "Mow The Lawn! [Simulator]": {
    "CCU": 743,
    "Visits": 86253839,
    "Ratio": 96
  },
  "Bear Simulator": {
    "CCU": 207,
    "Visits": 7166776,
    "Ratio": 88
  },
  "Drive and Crash Into People": {
    "CCU": 24,
    "Visits": 4525523,
    "Ratio": 81
  },
  "Be a Pirate": {
    "CCU": 38,
    "Visits": 1574850,
    "Ratio": 82
  },
  "Destroy It! Simulator": {
    "CCU": 50,
    "Visits": 19845364,
    "Ratio": 92
  },
  "Haikyuu Legends": {
    "CCU": 47020,
    "Visits": 59294212,
    "Ratio": 97
  },
  "Draw Tower Race": {
    "CCU": 1280,
    "Visits": 22011490,
    "Ratio": 86
  },
  "Be a Snake": {
    "CCU": 1103,
    "Visits": 72311625,
    "Ratio": 88
  }
}