{
  "Be a Tornado": {
    "CCU": 501,
    "Visits": 46632773,
    "Ratio": 91
  },
  "Ride a Cart Simulator": {
    "CCU": 660,
    "Visits": 149640734,
    "Ratio": 95
  },
  "Be a Snake": {
    "CCU": 1116,
    "Visits": 70227543,
    "Ratio": 88
  },
  "Be a Spider! Tycoon": {
    "CCU": 239,
    "Visits": 111824114,
    "Ratio": 92
  },
  "Be a Shark": {
    "CCU": 716,
    "Visits": 65862582,
    "Ratio": 88
  },
  "Mow The Lawn! [Simulator]": {
    "CCU": 309,
    "Visits": 85792796,
    "Ratio": 96
  },
  "EAT A FRIEND": {
    "CCU": 18,
    "Visits": 8848953,
    "Ratio": 89
  },
  "Destroy It! Simulator": {
    "CCU": 95,
    "Visits": 19740049,
    "Ratio": 92
  },
  "Draw Tower Race": {
    "CCU": 1907,
    "Visits": 19768857,
    "Ratio": 86
  },
  "Be a Dragon": {
    "CCU": 160,
    "Visits": 9310591,
    "Ratio": 89
  },
  "Bear Simulator": {
    "CCU": 85,
    "Visits": 6944779,
    "Ratio": 88
  },
  "Be a Tank": {
    "CCU": 283,
    "Visits": 11486298,
    "Ratio": 86
  },
  "Fire Fighting Simulator": {
    "CCU": 39,
    "Visits": 4943797,
    "Ratio": 88
  },
  "Be a Pirate": {
    "CCU": 35,
    "Visits": 1500678,
    "Ratio": 82
  },
  "Drive and Crash Into People": {
    "CCU": 22,
    "Visits": 4445081,
    "Ratio": 81
  },
  "Baby City! RP": {
    "CCU": 238,
    "Visits": 94985788,
    "Ratio": 77
  }
}